rasl/__init__.py
rasl/application.py
rasl/inner.py
rasl/jacobian.py
rasl/rasl.py
rasl/show.py
rasl/tform.py
rasl/toolbox.py
rasl/version.py
rasl-0.1.0.dist-info/DESCRIPTION.rst
rasl-0.1.0.dist-info/METADATA
rasl-0.1.0.dist-info/RECORD
rasl-0.1.0.dist-info/WHEEL
rasl-0.1.0.dist-info/entry_points.txt
rasl-0.1.0.dist-info/metadata.json
rasl-0.1.0.dist-info/top_level.txt
