Metadata-Version: 2.0
Name: rasl
Version: 0.1.0
Summary: Batch image alignment using the technique described in "Robust Alignment by Sparse and Low-rank Decomposition for Linearly Correlated Images"
Home-page: https://github.com/welch/rasl
Author: Will Welch
Author-email: github@quietplease.com
License: MIT
Keywords: Principal Component Pursuit,Robust PCA,Image alignment,Eigenface
Platform: UNKNOWN
Classifier: Development Status :: 4 - Beta
Classifier: License :: OSI Approved :: MIT License
Classifier: Programming Language :: Python :: 2.7
Classifier: Topic :: Scientific/Engineering
Requires-Dist: numpy
Requires-Dist: scikit-image
Requires-Dist: scipy
Provides-Extra: PLOT
Requires-Dist: matplotlib; extra == 'PLOT'
